email_reply_parser/__init__.py
email_reply_parser_jimmy927-0.6.2.dist-info/licenses/LICENSE
email_reply_parser_jimmy927-0.6.2.dist-info/METADATA
email_reply_parser_jimmy927-0.6.2.dist-info/WHEEL
email_reply_parser_jimmy927-0.6.2.dist-info/top_level.txt
email_reply_parser_jimmy927-0.6.2.dist-info/RECORD
