Metadata-Version: 2.4
Name: email-reply-parser-jimmy927
Version: 0.6.2
Summary: Email reply parser
Author-email: Jimmy Engelbrecht <jimmy@plero.se>
License: MIT
Project-URL: Homepage, https://github.com/jimmy927/email-reply-parser
Project-URL: Bug Tracker, https://github.com/jimmy927/email-reply-parser/issues
Classifier: Topic :: Software Development
Classifier: Programming Language :: Python
Classifier: Programming Language :: Python :: 3
Classifier: Programming Language :: Python :: 3.8
Classifier: Programming Language :: Python :: 3.9
Classifier: Programming Language :: Python :: 3.10
Classifier: Programming Language :: Python :: 3.11
Classifier: Programming Language :: Python :: 3.12
Classifier: Programming Language :: Python :: 3.13
Requires-Python: >=3.8
License-File: LICENSE
Dynamic: license-file
